tehut/__init__.py
tehut/normalisation.py
tehut-0.1.0.2.dist-info/WHEEL
tehut-0.1.0.2.dist-info/METADATA
tehut-0.1.0.2.dist-info/RECORD
