Metadata-Version: 2.1
Name: tehut
Version: 0.1.0.2
Summary: 
Author: Lennart Keller
Author-email: lennart.keller@googlemail.com
Requires-Python: >=3.8,<4.0
Classifier: Programming Language :: Python :: 3
Classifier: Programming Language :: Python :: 3.8
Classifier: Programming Language :: Python :: 3.9
Requires-Dist: more-itertools (>=8.10.0,<9.0.0)
Requires-Dist: requests (>=2.26.0,<3.0.0)
